foliant/preprocessors/utils/__init__.py
foliant/preprocessors/utils/preprocessor_ext.py
foliantcontrib.utils.preprocessor_ext-1.0.5.dist-info/LICENSE
foliantcontrib.utils.preprocessor_ext-1.0.5.dist-info/METADATA
foliantcontrib.utils.preprocessor_ext-1.0.5.dist-info/WHEEL
foliantcontrib.utils.preprocessor_ext-1.0.5.dist-info/top_level.txt
foliantcontrib.utils.preprocessor_ext-1.0.5.dist-info/RECORD
