Metadata-Version: 2.1
Name: foliantcontrib.utils.preprocessor-ext
Version: 1.0.5
Summary: Extension to basic preprocessor class with useful methods and functions.
Home-page: https://github.com/foliant-docs/foliantcontrib.utils.preprocessor_ext
Author: Daniil Minukhin
Author-email: ddddsa@gmail.com
License: MIT
Platform: any
Classifier: Development Status :: 5 - Production/Stable
Classifier: Environment :: Console
Classifier: Intended Audience :: Developers
Classifier: License :: OSI Approved :: MIT License
Classifier: Operating System :: OS Independent
Classifier: Programming Language :: Python
Classifier: Topic :: Documentation
Classifier: Topic :: Utilities
Requires-Dist: foliant (>=1.0.8)
Requires-Dist: foliantcontrib.meta (>=1.2.3)
Requires-Dist: PyYAML
